bcr/__init__.py
bcr/main.py
binarycookiesreader-0.0.1.dist-info/METADATA
binarycookiesreader-0.0.1.dist-info/WHEEL
binarycookiesreader-0.0.1.dist-info/entry_points.txt
binarycookiesreader-0.0.1.dist-info/top_level.txt
binarycookiesreader-0.0.1.dist-info/RECORD
