Metadata-Version: 2.1
Name: binarycookiesreader
Version: 0.0.1
Summary: Binarycookies Reader
Home-page: https://github.com/Sitoi/binarycookiesreader
Author: Sitoi
Author-email: 133397418@qq.com
License: MIT
Platform: UNKNOWN
Classifier: License :: OSI Approved :: MIT License
Classifier: Programming Language :: Python :: 3.6
Classifier: Programming Language :: Python :: 3.7
Classifier: Programming Language :: Python :: 3.8
Classifier: Programming Language :: Python :: 3.9
Classifier: Programming Language :: Python :: Implementation :: CPython
Classifier: Programming Language :: Python :: Implementation :: PyPy
Requires-Python: >=3.6.0
